setup.py
Products/__init__.py
Products.SmartPrintNG.egg-info/PKG-INFO
Products.SmartPrintNG.egg-info/SOURCES.txt
Products.SmartPrintNG.egg-info/dependency_links.txt
Products.SmartPrintNG.egg-info/namespace_packages.txt
Products.SmartPrintNG.egg-info/not-zip-safe
Products.SmartPrintNG.egg-info/requires.txt
Products.SmartPrintNG.egg-info/top_level.txt
Products/SmartPrintNG/CHANGES.txt
Products/SmartPrintNG/GPL3.txt
Products/SmartPrintNG/INSTALL.txt
Products/SmartPrintNG/LICENSE.txt
Products/SmartPrintNG/README.txt
Products/SmartPrintNG/TODO.txt
Products/SmartPrintNG/__init__.py
Products/SmartPrintNG/browser.py
Products/SmartPrintNG/config.py
Products/SmartPrintNG/configure.zcml
Products/SmartPrintNG/converters.py
Products/SmartPrintNG/header.txt
Products/SmartPrintNG/interfaces.py
Products/SmartPrintNG/meta.zcml
Products/SmartPrintNG/profiles.zcml
Products/SmartPrintNG/standard_extractor.py
Products/SmartPrintNG/version.txt
Products/SmartPrintNG/zcml.py
Products/SmartPrintNG/Extensions/Install.py
Products/SmartPrintNG/Extensions/__init__.py
Products/SmartPrintNG/converter/__init__.py
Products/SmartPrintNG/converter/configure.zcml
Products/SmartPrintNG/converter/default.py
Products/SmartPrintNG/converter/manipulation.py
Products/SmartPrintNG/converter/tests/__init__.py
Products/SmartPrintNG/converter/tests/testManipulation.py
Products/SmartPrintNG/demo/__init__.py
Products/SmartPrintNG/demo/configure.zcml
Products/SmartPrintNG/demo/plone_adapters.py
Products/SmartPrintNG/demo/document/document_demo.css
Products/SmartPrintNG/demo/document/document_template.pt
Products/SmartPrintNG/i18n/smartprintng-de.po
Products/SmartPrintNG/i18n/smartprintng-es.po
Products/SmartPrintNG/i18n/smartprintng-it.po
Products/SmartPrintNG/i18n/smartprintng-no.po
Products/SmartPrintNG/i18n/smartprintng-pt-br.po
Products/SmartPrintNG/i18n/smartprintng.pot
Products/SmartPrintNG/import/demo.zexp
Products/SmartPrintNG/profiles/default/actions.xml
Products/SmartPrintNG/profiles/default/cssregistry.xml
Products/SmartPrintNG/profiles/default/jsregistry.xml
Products/SmartPrintNG/profiles/default/skins.xml
Products/SmartPrintNG/profiles/plone31/actions.xml
Products/SmartPrintNG/profiles/plone31/cssregistry.xml
Products/SmartPrintNG/profiles/plone31/jsregistry.xml
Products/SmartPrintNG/profiles/plone31/skins.xml
