Metadata-Version: 1.0
Name: Products.SmartPrintNG
Version: 1.2.13
Summary: Produce & Publish for Plone - Conversion of Plone content to PDF, RTS, ODT, DOCX and WML
Home-page: http://opensource.zopyx.com/projects/SmartPrintNG
Author: Andreas Jung
Author-email: info@zopyx.com
License: LGPL 3
Keywords: PDF  RTF  ODT  DOCX  WML conversion Plone Zope Python
Platform: UNKNOWN
Classifier: Programming Language :: Python
Classifier: Framework :: Zope2
Classifier: Framework :: Plone
